TongguoLiziXueRust/README.md
TongguoLiziXueRust/__init__.py
TongguoLiziXueRust/__main__.py
TongguoLiziXueRust/file.epub
TongguoLiziXueRust/index.html
TongguoLiziXueRust/css/__init__.py
TongguoLiziXueRust/css/annotations.css
TongguoLiziXueRust/css/main.css
TongguoLiziXueRust/css/normalize.css
TongguoLiziXueRust/css/popup.css
TongguoLiziXueRust/font/__init__.py
TongguoLiziXueRust/font/fontello.eot
TongguoLiziXueRust/font/fontello.svg
TongguoLiziXueRust/font/fontello.ttf
TongguoLiziXueRust/font/fontello.woff
TongguoLiziXueRust/img/__init__.py
TongguoLiziXueRust/img/annotator-glyph-sprite.png
TongguoLiziXueRust/img/annotator-icon-sprite.png
TongguoLiziXueRust/img/apple-touch-icon.png
TongguoLiziXueRust/img/cancelfullscreen.png
TongguoLiziXueRust/img/close.png
TongguoLiziXueRust/img/fullscreen.png
TongguoLiziXueRust/img/loader.gif
TongguoLiziXueRust/img/menu-icon.png
TongguoLiziXueRust/img/save.png
TongguoLiziXueRust/img/saved.png
TongguoLiziXueRust/img/settings-s.png
TongguoLiziXueRust/img/settings.png
TongguoLiziXueRust/img/star.png
TongguoLiziXueRust/js/__init__.py
TongguoLiziXueRust/js/epub.js
TongguoLiziXueRust/js/epub.min.js
TongguoLiziXueRust/js/epub.min.map
TongguoLiziXueRust/js/hooks.min.js
TongguoLiziXueRust/js/hooks.min.map
TongguoLiziXueRust/js/reader.js
TongguoLiziXueRust/js/reader.js.map
TongguoLiziXueRust/js/reader.min.js
TongguoLiziXueRust/js/reader.min.map
TongguoLiziXueRust/js/hooks/__init__.py
TongguoLiziXueRust/js/hooks/extensions/__init__.py
TongguoLiziXueRust/js/hooks/extensions/highlight.js
TongguoLiziXueRust/js/libs/__init__.py
TongguoLiziXueRust/js/libs/jquery.min.js
TongguoLiziXueRust/js/libs/localforage.min.js
TongguoLiziXueRust/js/libs/screenfull.js
TongguoLiziXueRust/js/libs/screenfull.min.js
TongguoLiziXueRust/js/libs/zip.min.js
TongguoLiziXueRust/js/plugins/__init__.py
TongguoLiziXueRust/js/plugins/hypothesis.js
TongguoLiziXueRust/js/plugins/search.js
tongguo_lizi_xue_rust-2024.3.6.0.dist-info/METADATA
tongguo_lizi_xue_rust-2024.3.6.0.dist-info/WHEEL
tongguo_lizi_xue_rust-2024.3.6.0.dist-info/entry_points.txt
tongguo_lizi_xue_rust-2024.3.6.0.dist-info/top_level.txt
tongguo_lizi_xue_rust-2024.3.6.0.dist-info/RECORD
